dbt_conceptual/__init__.py
dbt_conceptual/cli.py
dbt_conceptual/config.py
dbt_conceptual/diff_formatter.py
dbt_conceptual/differ.py
dbt_conceptual/parser.py
dbt_conceptual/scanner.py
dbt_conceptual/server.py
dbt_conceptual/state.py
dbt_conceptual/validator.py
dbt_conceptual/exporter/__init__.py
dbt_conceptual/exporter/bus_matrix.py
dbt_conceptual/exporter/coverage.py
dbt_conceptual/exporter/png.py
dbt_conceptual/static/favicon-16x16.png
dbt_conceptual/static/favicon-32x32.png
dbt_conceptual/static/favicon-48x48.png
dbt_conceptual/static/favicon.ico
dbt_conceptual/static/favicon.png
dbt_conceptual/static/favicon.svg
dbt_conceptual/static/index.html
dbt_conceptual/static/assets/index-B2_oi_cO.js
dbt_conceptual/static/assets/index-BbkpIdDx.css
dbt_conceptual-0.5.5.dist-info/METADATA
dbt_conceptual-0.5.5.dist-info/WHEEL
dbt_conceptual-0.5.5.dist-info/entry_points.txt
dbt_conceptual-0.5.5.dist-info/licenses/LICENSE
dbt_conceptual-0.5.5.dist-info/RECORD
