Metadata-Version: 2.4
Name: dbt-conceptual
Version: 0.5.5
Summary: Bridge the gap between conceptual models and your lakehouse
Project-URL: Homepage, https://github.com/feriksen-personal/dbt-conceptual
Project-URL: Repository, https://github.com/feriksen-personal/dbt-conceptual
Project-URL: Issues, https://github.com/feriksen-personal/dbt-conceptual/issues
Project-URL: Changelog, https://github.com/feriksen-personal/dbt-conceptual/blob/main/CHANGELOG.md
Author-email: Fridthjof-Greger Eriksen <fridthjof.eriksen@gmail.com>
License-Expression: MIT
License-File: LICENSE
Keywords: conceptual-model,data-architecture,data-modeling,databricks,dbt,lakehouse,medallion,snowflake
Classifier: Development Status :: 4 - Beta
Classifier: Environment :: Console
Classifier: Intended Audience :: Developers
Classifier: Intended Audience :: Information Technology
Classifier: License :: OSI Approved :: MIT License
Classifier: Operating System :: OS Independent
Classifier: Programming Language :: Python :: 3
Classifier: Programming Language :: Python :: 3.9
Classifier: Programming Language :: Python :: 3.10
Classifier: Programming Language :: Python :: 3.11
Classifier: Programming Language :: Python :: 3.12
Classifier: Topic :: Database
Classifier: Topic :: Software Development :: Documentation
Classifier: Typing :: Typed
Requires-Python: >=3.9
Requires-Dist: click>=8.0
Requires-Dist: playwright>=1.40
Requires-Dist: pyyaml>=6.0
Requires-Dist: rich>=13.0
Provides-Extra: all
Requires-Dist: black>=24.0; extra == 'all'
Requires-Dist: flask>=3.0; extra == 'all'
Requires-Dist: mkdocs-material>=9.0; extra == 'all'
Requires-Dist: mkdocs>=1.5; extra == 'all'
Requires-Dist: mypy>=1.0; extra == 'all'
Requires-Dist: pytest-cov>=4.0; extra == 'all'
Requires-Dist: pytest>=7.0; extra == 'all'
Requires-Dist: ruff>=0.1.0; extra == 'all'
Requires-Dist: types-pyyaml; extra == 'all'
Provides-Extra: dev
Requires-Dist: black>=24.0; extra == 'dev'
Requires-Dist: mypy>=1.0; extra == 'dev'
Requires-Dist: pytest-cov>=4.0; extra == 'dev'
Requires-Dist: pytest>=7.0; extra == 'dev'
Requires-Dist: ruff>=0.1.0; extra == 'dev'
Requires-Dist: types-pyyaml; extra == 'dev'
Provides-Extra: docs
Requires-Dist: mkdocs-material>=9.0; extra == 'docs'
Requires-Dist: mkdocs>=1.5; extra == 'docs'
Provides-Extra: serve
Requires-Dist: flask>=3.0; extra == 'serve'
